cadenza_example_sdk/__init__.py
cadenza_example_sdk/_base_client.py
cadenza_example_sdk/_client.py
cadenza_example_sdk/_compat.py
cadenza_example_sdk/_constants.py
cadenza_example_sdk/_exceptions.py
cadenza_example_sdk/_files.py
cadenza_example_sdk/_models.py
cadenza_example_sdk/_qs.py
cadenza_example_sdk/_resource.py
cadenza_example_sdk/_response.py
cadenza_example_sdk/_streaming.py
cadenza_example_sdk/_types.py
cadenza_example_sdk/_version.py
cadenza_example_sdk/pagination.py
cadenza_example_sdk/py.typed
cadenza_example_sdk/_utils/__init__.py
cadenza_example_sdk/_utils/_logs.py
cadenza_example_sdk/_utils/_proxy.py
cadenza_example_sdk/_utils/_reflection.py
cadenza_example_sdk/_utils/_streams.py
cadenza_example_sdk/_utils/_sync.py
cadenza_example_sdk/_utils/_transform.py
cadenza_example_sdk/_utils/_typing.py
cadenza_example_sdk/_utils/_utils.py
cadenza_example_sdk/lib/.keep
cadenza_example_sdk/resources/__init__.py
cadenza_example_sdk/resources/exchange_accounts.py
cadenza_example_sdk/resources/health.py
cadenza_example_sdk/resources/portfolio.py
cadenza_example_sdk/resources/clients/__init__.py
cadenza_example_sdk/resources/clients/clients.py
cadenza_example_sdk/resources/clients/info.py
cadenza_example_sdk/resources/market/__init__.py
cadenza_example_sdk/resources/market/instrument.py
cadenza_example_sdk/resources/market/kline.py
cadenza_example_sdk/resources/market/market.py
cadenza_example_sdk/resources/market/orderbook.py
cadenza_example_sdk/resources/market/ticker.py
cadenza_example_sdk/resources/trading/__init__.py
cadenza_example_sdk/resources/trading/execution_report.py
cadenza_example_sdk/resources/trading/order.py
cadenza_example_sdk/resources/trading/quote.py
cadenza_example_sdk/resources/trading/trading.py
cadenza_example_sdk/types/__init__.py
cadenza_example_sdk/types/exchange_account.py
cadenza_example_sdk/types/exchange_account_balance.py
cadenza_example_sdk/types/exchange_account_create_params.py
cadenza_example_sdk-0.1.0a3.dist-info/METADATA
cadenza_example_sdk-0.1.0a3.dist-info/WHEEL
cadenza_example_sdk-0.1.0a3.dist-info/licenses/LICENSE
cadenza_example_sdk-0.1.0a3.dist-info/RECORD
